silk/__init__.py
silk/actions/__init__.py
silk/actions/browser.py
silk/actions/elements.py
silk/actions/input.py
silk/actions/navigation.py
silk/actions/py.typed
silk/actions/utils.py
silk/browsers/__init__.py
silk/browsers/drivers/__init__.py
silk/browsers/drivers/playwright.py
silk/browsers/models.py
silk/browsers/py.typed
silk/browsers/sessions.py
silk/composition.py
silk/flow.py
silk/objects.py
silk/operation.py
silk/placeholder.py
silk/py.typed
silk/selectors/__init__.py
silk/selectors/py.typed
silk/selectors/selector.py
silk/text.py
silk/utils.py
silk_scraper-0.3.1.dist-info/LICENSE
silk_scraper-0.3.1.dist-info/METADATA
silk_scraper-0.3.1.dist-info/WHEEL
silk_scraper-0.3.1.dist-info/RECORD
