Metadata-Version: 2.3
Name: silk-scraper
Version: 0.3.1
Summary: A flexible browser automation library with support for multiple drivers
License: MIT
Author: Galad Dirie
Author-email: hello@galad.ca
Requires-Python: >=3.11,<4.0
Classifier: Development Status :: 4 - Beta
Classifier: Intended Audience :: Developers
Classifier: License :: OSI Approved :: MIT License
Classifier: Programming Language :: Python :: 3
Classifier: Programming Language :: Python :: 3.11
Classifier: Programming Language :: Python :: 3.12
Classifier: Programming Language :: Python :: 3.13
Classifier: Topic :: Software Development :: Libraries :: Python Modules
Classifier: Topic :: Internet :: WWW/HTTP :: Browsers
Provides-Extra: all
Provides-Extra: patchright
Provides-Extra: playwright
Requires-Dist: expression (>=5.6.0,<6.0.0)
Requires-Dist: fp-ops (>=0.1.3,<1.0.0)
Requires-Dist: patchright (>=1.51.0,<2.0.0) ; extra == "all"
Requires-Dist: patchright (>=1.51.0,<2.0.0) ; extra == "patchright"
Requires-Dist: playwright (>=1.51.0,<2.0.0)
Requires-Dist: playwright (>=1.51.0,<2.0.0) ; extra == "all"
Requires-Dist: playwright (>=1.51.0,<2.0.0) ; extra == "playwright"
Requires-Dist: pydantic (>=2.11.2,<3.0.0)
Requires-Dist: pydantic-settings (>=2.8.1,<3.0.0)
Project-URL: Bug Tracker, https://github.com/galaddirie/silk/issues
Project-URL: Homepage, https://github.com/galaddirie/silk
